jaxspec/__init__.py
jaxspec/analysis/__init__.py
jaxspec/analysis/_plot.py
jaxspec/analysis/compare.py
jaxspec/analysis/results.py
jaxspec/data/__init__.py
jaxspec/data/instrument.py
jaxspec/data/obsconf.py
jaxspec/data/observation.py
jaxspec/data/ogip.py
jaxspec/data/util.py
jaxspec/experimental/__init__.py
jaxspec/experimental/interpolator.py
jaxspec/experimental/interpolator_jax.py
jaxspec/experimental/intrument_models.py
jaxspec/experimental/nested_sampler.py
jaxspec/experimental/tabulated.py
jaxspec/fit/__init__.py
jaxspec/fit/_bayesian_model.py
jaxspec/fit/_build_model.py
jaxspec/fit/_fitter.py
jaxspec/model/__init__.py
jaxspec/model/_graph_util.py
jaxspec/model/abc.py
jaxspec/model/additive.py
jaxspec/model/background.py
jaxspec/model/instrument.py
jaxspec/model/list.py
jaxspec/model/multiplicative.py
jaxspec/scripts/__init__.py
jaxspec/scripts/debug.py
jaxspec/util/__init__.py
jaxspec/util/abundance.py
jaxspec/util/integrate.py
jaxspec/util/misc.py
jaxspec/util/online_storage.py
jaxspec/util/typing.py
jaxspec-0.3.3.dist-info/METADATA
jaxspec-0.3.3.dist-info/WHEEL
jaxspec-0.3.3.dist-info/entry_points.txt
jaxspec-0.3.3.dist-info/licenses/LICENSE.md
jaxspec-0.3.3.dist-info/RECORD
