Metadata-Version: 2.4
Name: jaxspec
Version: 0.3.3
Summary: jaxspec is a bayesian spectral fitting library for X-ray astronomy.
Project-URL: Homepage, https://github.com/renecotyfanboy/jaxspec
Project-URL: Documentation, https://jaxspec.readthedocs.io/en/latest/
Author-email: sdupourque <sdupourque@irap.omp.eu>
License-Expression: MIT
License-File: LICENSE.md
Requires-Python: <3.13,>=3.10
Requires-Dist: arviz<0.23.0,>=0.17.1
Requires-Dist: astropy<8,>=6.0.0
Requires-Dist: catppuccin<3,>=2.3.4
Requires-Dist: chainconsumer<2,>=1.1.2
Requires-Dist: cmasher<2,>=1.6.3
Requires-Dist: flax>0.10.5
Requires-Dist: interpax<0.4,>=0.3.5
Requires-Dist: jax<0.7,>=0.5.0
Requires-Dist: matplotlib<4,>=3.8.0
Requires-Dist: mendeleev<1.2,>=0.15
Requires-Dist: networkx~=3.1
Requires-Dist: numpy<3.0.0
Requires-Dist: numpyro<0.20,>=0.17.0
Requires-Dist: pandas<3,>=2.2.0
Requires-Dist: pooch<2,>=1.8.2
Requires-Dist: scipy<1.16
Requires-Dist: seaborn>=0.13.2
Requires-Dist: sparse>0.15
Requires-Dist: tinygp<0.4,>=0.3.0
Requires-Dist: watermark<3,>=2.4.3
